[
  {
    "LinkSabrCheck": "https://www.baseball-reference.com/boxes/BOS/BOS194607142.shtml",
    "Author": "TEST",
    "LinkBox": "https://www.baseball-reference.com/boxes/PHI/PHI197209160.shtml",
    "Date": "2026-01-26",
    "Series": "2026-01-26",
    "id": "0",
    "baseballRefKey": "na",
    "gameDateKey": "na",
    "AwayTeam": "0",
    "HomeTeam": "0",
    "AwayRunsScored": "0",
    "AwayHits": "0",
    "AwayErrors": "0",
    "HomeRunsScored": "0",
    "HomeHits": "0",
    "HomeErrors": "0",
    "A1_Name": "To BEGIN",
    "A2_Name": "_",
    "A3_Name": "#starting9",
    "A4_Name": "YELLOW",
    "A5_Name": "button",
    "A6_Name": "_",
    "A7_Name": "_",
    "A8_Name": "_",
    "A9_Name": "_",
    "A10_Name": "_",
    "A1_Pos": "_",
    "A2_Pos": "_",
    "A3_Pos": "_",
    "A4_Pos": "_",
    "A5_Pos": "_",
    "A6_Pos": "_",
    "A7_Pos": "_",
    "A8_Pos": "LINEUP",
    "A9_Pos": "_",
    "A10_Pos": "playing",
    "H1_Name": "_",
    "H2_Name": "press",
    "H3_Name": "START",
    "H4_Name": "Above",
    "H5_Name": "_",
    "H6_Name": "_",
    "H7_Name": "_",
    "H8_Name": "_",
    "H9_Name": "_",
    "H10_Name": "_",
    "H1_Pos": "_",
    "H2_Pos": "_",
    "H3_Pos": "_",
    "H4_Pos": "_",
    "H5_Pos": "_",
    "H6_Pos": "_",
    "H7_Pos": "_",
    "H8_Pos": "-",
    "H9_Pos": "na",
    "H10_Pos": "na",
    "LinkSabr": "https://sabr.org/gamesproj/game/milwaukee-braves-make-dramatic-comeback-in-9th-win-in-11/"
  },
  {
    "LinkSabrCheck": "https://sabr.org/gamesproj/game/september-29-2024-red-sox-beat-rays-in-the-battle-for-500-to-end-the-season/",
    "Author": "https://sabr.org/authors/bill-nowlin/",
    "LinkBox": "https://www.baseball-reference.com/boxes/BOS/BOS202409290.shtml",
    "Date": "2026-01-26",
    "Series": "2026-01-26",
    "id": "1",
    "baseballRefKey": "BOS202409290",
    "gameDateKey": "BOS202409290",
    "AwayTeam": "Tampa Bay Rays (1998-present)",
    "HomeTeam": "Boston Red Sox (1901-present)",
    "AwayRunsScored": "1",
    "AwayHits": "8",
    "AwayErrors": "2",
    "HomeRunsScored": "3",
    "HomeHits": "7",
    "HomeErrors": "1",
    "A1_Name": "Palacios",
    "A2_Name": "Caminero",
    "A3_Name": "Aranda",
    "A4_Name": "Morel",
    "A5_Name": "Lowe",
    "A6_Name": "DeLuca",
    "A7_Name": "Carlson",
    "A8_Name": "Caballero",
    "A9_Name": "Driscoll",
    "A10_Name": "Pepiot",
    "A1_Pos": "2b",
    "A2_Pos": "3b",
    "A3_Pos": "1b",
    "A4_Pos": "lf",
    "A5_Pos": "rf",
    "A6_Pos": "cf",
    "A7_Pos": "dh",
    "A8_Pos": "ss",
    "A9_Pos": "c",
    "A10_Pos": "p",
    "H1_Name": "Duran",
    "H2_Name": "Grissom",
    "H3_Name": "Casas",
    "H4_Name": "Wong",
    "H5_Name": "Abreu",
    "H6_Name": "Sogard",
    "H7_Name": "Rafaela",
    "H8_Name": "Gasper",
    "H9_Name": "Valdez",
    "H10_Name": "Priester",
    "H1_Pos": "lf",
    "H2_Pos": "2b",
    "H3_Pos": "1b",
    "H4_Pos": "c",
    "H5_Pos": "rf",
    "H6_Pos": "ss",
    "H7_Pos": "cf",
    "H8_Pos": "dh",
    "H9_Pos": "3b",
    "H10_Pos": "p",
    "LinkSabr": "https://sabr.org/gamesproj/game/september-29-2024-red-sox-beat-rays-in-the-battle-for-500-to-end-the-season/"
  },
  {
    "LinkSabrCheck": "https://sabr.org/gamesproj/game/may-12-1915-fading-christy-mathewson-holds-off-reds-for-his-first-win-of-season/",
    "Author": "https://sabr.org/authors/kurt-blumenau/",
    "LinkBox": "https://www.baseball-reference.com/boxes/NY1/NY1191505120.shtml",
    "Date": "2026-01-26",
    "Series": "2026-01-26",
    "id": "2",
    "baseballRefKey": "NY1191505120",
    "gameDateKey": "NY1191505120",
    "AwayTeam": "Cincinnati Reds (1882-present)",
    "HomeTeam": "New York Giants (1883-1957)",
    "AwayRunsScored": "5",
    "AwayHits": "11",
    "AwayErrors": "3",
    "HomeRunsScored": "6",
    "HomeHits": "11",
    "HomeErrors": "1",
    "A1_Name": "Leach",
    "A2_Name": "Groh",
    "A3_Name": "Twombly",
    "A4_Name": "Griffith",
    "A5_Name": "Wagner",
    "A6_Name": "Olson",
    "A7_Name": "Mollwitz",
    "A8_Name": "Clarke",
    "A9_Name": "Dale",
    "A10_Name": "none",
    "A1_Pos": "cf",
    "A2_Pos": "3b",
    "A3_Pos": "lf",
    "A4_Pos": "rf",
    "A5_Pos": "ss",
    "A6_Pos": "2b",
    "A7_Pos": "1b",
    "A8_Pos": "c",
    "A9_Pos": "p",
    "A10_Pos": "dh",
    "H1_Name": "Burns",
    "H2_Name": "Doyle",
    "H3_Name": "Lobert",
    "H4_Name": "Fletcher",
    "H5_Name": "Robertson",
    "H6_Name": "Brainard",
    "H7_Name": "Meyers",
    "H8_Name": "Murray",
    "H9_Name": "Mathewson",
    "H10_Name": "none",
    "H1_Pos": "lf",
    "H2_Pos": "2b",
    "H3_Pos": "3b",
    "H4_Pos": "ss",
    "H5_Pos": "rf",
    "H6_Pos": "1b",
    "H7_Pos": "c",
    "H8_Pos": "cf",
    "H9_Pos": "p",
    "H10_Pos": "dh",
    "LinkSabr": "https://sabr.org/gamesproj/game/may-12-1915-fading-christy-mathewson-holds-off-reds-for-his-first-win-of-season/"
  },
  {
    "LinkSabrCheck": "https://sabr.org/gamesproj/game/august-14-1965-koufax-spins-shutout-clemente-commits-costly-error-as-los-angeles-riots/",
    "Author": "https://sabr.org/authors/gregory-h-wolf/",
    "LinkBox": "https://www.baseball-reference.com/boxes/LAN/LAN196508140.shtml",
    "Date": "2026-01-26",
    "Series": "2026-01-26",
    "id": "3",
    "baseballRefKey": "LAN196508140",
    "gameDateKey": "LAN196508140",
    "AwayTeam": "Pittsburgh Pirates (1882-present)",
    "HomeTeam": "Los Angeles Dodgers (1884-present)",
    "AwayRunsScored": "0",
    "AwayHits": "5",
    "AwayErrors": "1",
    "HomeRunsScored": "1",
    "HomeHits": "5",
    "HomeErrors": "1",
    "A1_Name": "Bailey",
    "A2_Name": "Mota",
    "A3_Name": "Clemente",
    "A4_Name": "Clendenon",
    "A5_Name": "Mazeroski",
    "A6_Name": "Stargell",
    "A7_Name": "Pagliaroni",
    "A8_Name": "Alley",
    "A9_Name": "Cardwell",
    "A10_Name": "none",
    "A1_Pos": "3b",
    "A2_Pos": "cf",
    "A3_Pos": "rf",
    "A4_Pos": "1b",
    "A5_Pos": "2b",
    "A6_Pos": "lf",
    "A7_Pos": "c",
    "A8_Pos": "ss",
    "A9_Pos": "p",
    "A10_Pos": "dh",
    "H1_Name": "Parker",
    "H2_Name": "Gilliam",
    "H3_Name": "Lefebvre",
    "H4_Name": "Fairly",
    "H5_Name": "Johnson",
    "H6_Name": "Davis",
    "H7_Name": "Roseboro",
    "H8_Name": "Kennedy",
    "H9_Name": "Koufax",
    "H10_Name": "none",
    "H1_Pos": "1b",
    "H2_Pos": "3b",
    "H3_Pos": "2b",
    "H4_Pos": "rf",
    "H5_Pos": "lf",
    "H6_Pos": "cf",
    "H7_Pos": "c",
    "H8_Pos": "ss",
    "H9_Pos": "p",
    "H10_Pos": "dh",
    "LinkSabr": "https://sabr.org/gamesproj/game/august-14-1965-koufax-spins-shutout-clemente-commits-costly-error-as-los-angeles-riots/"
  },
  {
    "LinkSabrCheck": "https://sabr.org/gamesproj/game/june-22-1974-ron-schuelers-complete-game-leads-phillies-in-opener/",
    "Author": "https://sabr.org/authors/steven-glassman/",
    "LinkBox": "https://www.baseball-reference.com/boxes/PHI/PHI197406221.shtml",
    "Date": "2026-01-26",
    "Series": "2026-01-26",
    "id": "4",
    "baseballRefKey": "PHI197406221",
    "gameDateKey": "PHI197406221",
    "AwayTeam": "New York Mets (1962-present)",
    "HomeTeam": "Philadelphia Phillies (1883-present)",
    "AwayRunsScored": "2",
    "AwayHits": "5",
    "AwayErrors": "0",
    "HomeRunsScored": "5",
    "HomeHits": "12",
    "HomeErrors": "1",
    "A1_Name": "Garrett",
    "A2_Name": "Millan",
    "A3_Name": "Jones",
    "A4_Name": "Staub",
    "A5_Name": "Milner",
    "A6_Name": "Boswell",
    "A7_Name": "Schneck",
    "A8_Name": "Grote",
    "A9_Name": "Parker",
    "A10_Name": "none",
    "A1_Pos": "ss",
    "A2_Pos": "2b",
    "A3_Pos": "lf",
    "A4_Pos": "rf",
    "A5_Pos": "1b",
    "A6_Pos": "3b",
    "A7_Pos": "cf",
    "A8_Pos": "c",
    "A9_Pos": "p",
    "A10_Pos": "dh",
    "H1_Name": "Cash",
    "H2_Name": "Bowa",
    "H3_Name": "Unser",
    "H4_Name": "Schmidt",
    "H5_Name": "Hutton",
    "H6_Name": "Anderson",
    "H7_Name": "Montanez",
    "H8_Name": "Boone",
    "H9_Name": "Schueler",
    "H10_Name": "none",
    "H1_Pos": "2b",
    "H2_Pos": "ss",
    "H3_Pos": "cf",
    "H4_Pos": "3b",
    "H5_Pos": "lf",
    "H6_Pos": "rf",
    "H7_Pos": "1b",
    "H8_Pos": "c",
    "H9_Pos": "p",
    "H10_Pos": "dh",
    "LinkSabr": "https://sabr.org/gamesproj/game/june-22-1974-ron-schuelers-complete-game-leads-phillies-in-opener/"
  },
  {
    "LinkSabrCheck": "https://sabr.org/gamesproj/game/september-9-1914-chicago-battles-buffalo-to-12-inning-tie/",
    "Author": "https://sabr.org/authors/brian-frank/",
    "LinkBox": "https://www.baseball-reference.com/boxes/BUF/BUF191409090.shtml",
    "Date": "2026-01-26",
    "Series": "2026-01-26",
    "id": "5",
    "baseballRefKey": "BUF191409090",
    "gameDateKey": "BUF191409090",
    "AwayTeam": "Chicago Whales/Chi-Feds (FL 1914-1915)",
    "HomeTeam": "Buffalo Buffeds/Blues/Bisons (FL 1914-1915)",
    "AwayRunsScored": "5",
    "AwayHits": "11",
    "AwayErrors": "3",
    "HomeRunsScored": "5",
    "HomeHits": "13",
    "HomeErrors": "1",
    "A1_Name": "Flack",
    "A2_Name": "Zeider",
    "A3_Name": "Wilson",
    "A4_Name": "Zwilling",
    "A5_Name": "Wickland",
    "A6_Name": "Tinker",
    "A7_Name": "Beck",
    "A8_Name": "Farrell",
    "A9_Name": "Lange",
    "A10_Name": "none",
    "A1_Pos": "rf",
    "A2_Pos": "3b",
    "A3_Pos": "c",
    "A4_Pos": "cf",
    "A5_Pos": "lf",
    "A6_Pos": "ss",
    "A7_Pos": "1b",
    "A8_Pos": "2b",
    "A9_Pos": "p",
    "A10_Pos": "dh",
    "H1_Name": "Agler",
    "H2_Name": "Downey",
    "H3_Name": "Louden",
    "H4_Name": "McDonald",
    "H5_Name": "Chase",
    "H6_Name": "Hanford",
    "H7_Name": "Smith",
    "H8_Name": "LaVigne",
    "H9_Name": "Anderson",
    "H10_Name": "none",
    "H1_Pos": "lf",
    "H2_Pos": "2b",
    "H3_Pos": "ss",
    "H4_Pos": "rf",
    "H5_Pos": "1b",
    "H6_Pos": "cf",
    "H7_Pos": "3b",
    "H8_Pos": "c",
    "H9_Pos": "p",
    "H10_Pos": "dh",
    "LinkSabr": "https://sabr.org/gamesproj/game/september-9-1914-chicago-battles-buffalo-to-12-inning-tie/"
  },
  {
    "LinkSabrCheck": "https://sabr.org/gamesproj/game/september-1-1998-yankees-david-wells-flirts-with-second-perfect-game-of-the-season/",
    "Author": "https://sabr.org/authors/harrison-golden/",
    "LinkBox": "https://www.baseball-reference.com/boxes/NYA/NYA199809010.shtml",
    "Date": "2026-01-26",
    "Series": "2026-01-26",
    "id": "6",
    "baseballRefKey": "NYA199809010",
    "gameDateKey": "NYA199809010",
    "AwayTeam": "Oakland Athletics (1901-present)",
    "HomeTeam": "New York Yankees (1903-present)",
    "AwayRunsScored": "0",
    "AwayHits": "2",
    "AwayErrors": "0",
    "HomeRunsScored": "7",
    "HomeHits": "12",
    "HomeErrors": "0",
    "A1_Name": "Henderson",
    "A2_Name": "Christenson",
    "A3_Name": "Giambi",
    "A4_Name": "Stairs",
    "A5_Name": "Blowers",
    "A6_Name": "Grieve",
    "A7_Name": "Spiezio",
    "A8_Name": "Tejada",
    "A9_Name": "Hinch",
    "A10_Name": "Candiotti",
    "A1_Pos": "lf",
    "A2_Pos": "cf",
    "A3_Pos": "1b",
    "A4_Pos": "dh",
    "A5_Pos": "3b",
    "A6_Pos": "rf",
    "A7_Pos": "2b",
    "A8_Pos": "ss",
    "A9_Pos": "c",
    "A10_Pos": "p",
    "H1_Name": "Knoblauch",
    "H2_Name": "Jeter",
    "H3_Name": "O'Neill",
    "H4_Name": "Williams",
    "H5_Name": "Martinez",
    "H6_Name": "Strawberry",
    "H7_Name": "Raines",
    "H8_Name": "Posada",
    "H9_Name": "Sojo",
    "H10_Name": "Wells",
    "H1_Pos": "2b",
    "H2_Pos": "ss",
    "H3_Pos": "rf",
    "H4_Pos": "cf",
    "H5_Pos": "1b",
    "H6_Pos": "dh",
    "H7_Pos": "lf",
    "H8_Pos": "c",
    "H9_Pos": "3b",
    "H10_Pos": "p",
    "LinkSabr": "https://sabr.org/gamesproj/game/september-1-1998-yankees-david-wells-flirts-with-second-perfect-game-of-the-season/"
  },
  {
    "LinkSabrCheck": "https://sabr.org/gamesproj/game/july-29-1951-player-manager-phil-cavarrettas-grand-slam-caps-cubs-doubleheader-sweep-of-phillies/",
    "Author": "https://sabr.org/authors/steve-dunn/",
    "LinkBox": "https://www.baseball-reference.com/boxes/CHN/CHN195107292.shtml",
    "Date": "2026-01-26",
    "Series": "2026-01-26",
    "id": "7",
    "baseballRefKey": "CHN195107292",
    "gameDateKey": "CHN195107292",
    "AwayTeam": "Philadelphia Phillies (1883-present)",
    "HomeTeam": "Chicago Cubs (1876-present)",
    "AwayRunsScored": "6",
    "AwayHits": "8",
    "AwayErrors": "2",
    "HomeRunsScored": "8",
    "HomeHits": "12",
    "HomeErrors": "2",
    "A1_Name": "Waitkus",
    "A2_Name": "Ashburn",
    "A3_Name": "Jones",
    "A4_Name": "Ennis",
    "A5_Name": "Sisler",
    "A6_Name": "Hamner",
    "A7_Name": "Pellagrini",
    "A8_Name": "Wilber",
    "A9_Name": "Thompson",
    "A10_Name": "none",
    "A1_Pos": "1b",
    "A2_Pos": "cf",
    "A3_Pos": "3b",
    "A4_Pos": "rf",
    "A5_Pos": "lf",
    "A6_Pos": "ss",
    "A7_Pos": "2b",
    "A8_Pos": "c",
    "A9_Pos": "p",
    "A10_Pos": "dh",
    "H1_Name": "Miksis",
    "H2_Name": "Jeffcoat",
    "H3_Name": "Baumholtz",
    "H4_Name": "Sauer",
    "H5_Name": "Jackson",
    "H6_Name": "Smalley",
    "H7_Name": "Connors",
    "H8_Name": "Owen",
    "H9_Name": "Rush",
    "H10_Name": "none",
    "H1_Pos": "2b",
    "H2_Pos": "rf",
    "H3_Pos": "cf",
    "H4_Pos": "lf",
    "H5_Pos": "3b",
    "H6_Pos": "ss",
    "H7_Pos": "1b",
    "H8_Pos": "c",
    "H9_Pos": "p",
    "H10_Pos": "dh",
    "LinkSabr": "https://sabr.org/gamesproj/game/july-29-1951-player-manager-phil-cavarrettas-grand-slam-caps-cubs-doubleheader-sweep-of-phillies/"
  },
  {
    "LinkSabrCheck": "https://sabr.org/gamesproj/game/april-29-2007-troy-tulowitzkis-unassisted-triple-play-and-matt-hollidays-walk-off-homer-lead-rockies-over-braves/",
    "Author": "https://sabr.org/authors/bill-marston/",
    "LinkBox": "https://www.baseball-reference.com/boxes/COL/COL200704290.shtml",
    "Date": "2026-01-26",
    "Series": "2026-01-26",
    "id": "8",
    "baseballRefKey": "COL200704290",
    "gameDateKey": "COL200704290",
    "AwayTeam": "Atlanta Braves (1876-present)",
    "HomeTeam": "Colorado Rockies (1993-present)",
    "AwayRunsScored": "7",
    "AwayHits": "16",
    "AwayErrors": "1",
    "HomeRunsScored": "9",
    "HomeHits": "8",
    "HomeErrors": "1",
    "A1_Name": "Johnson",
    "A2_Name": "Renteria",
    "A3_Name": "Jones",
    "A4_Name": "Jones",
    "A5_Name": "Francoeur",
    "A6_Name": "Thorman",
    "A7_Name": "Pena",
    "A8_Name": "Langerhans",
    "A9_Name": "Davies",
    "A10_Name": "none",
    "A1_Pos": "2b",
    "A2_Pos": "ss",
    "A3_Pos": "3b",
    "A4_Pos": "cf",
    "A5_Pos": "rf",
    "A6_Pos": "1b",
    "A7_Pos": "c",
    "A8_Pos": "lf",
    "A9_Pos": "p",
    "A10_Pos": "dh",
    "H1_Name": "Taveras",
    "H2_Name": "Tulowitzki",
    "H3_Name": "Atkins",
    "H4_Name": "Helton",
    "H5_Name": "Holliday",
    "H6_Name": "Hawpe",
    "H7_Name": "Iannetta",
    "H8_Name": "Carroll",
    "H9_Name": "Cook",
    "H10_Name": "none",
    "H1_Pos": "cf",
    "H2_Pos": "ss",
    "H3_Pos": "3b",
    "H4_Pos": "1b",
    "H5_Pos": "lf",
    "H6_Pos": "rf",
    "H7_Pos": "c",
    "H8_Pos": "2b",
    "H9_Pos": "p",
    "H10_Pos": "dh",
    "LinkSabr": "https://sabr.org/gamesproj/game/april-29-2007-troy-tulowitzkis-unassisted-triple-play-and-matt-hollidays-walk-off-homer-lead-rockies-over-braves/"
  },
  {
    "LinkSabrCheck": "https://sabr.org/gamesproj/game/october-9-1934-a-case-for-judge-landis-medwick-tossed-in-world-series-melee-as-cardinals-win-game-7/",
    "Author": "https://sabr.org/authors/brent-heutmaker/",
    "LinkBox": "https://www.baseball-reference.com/boxes/DET/DET193410090.shtml",
    "Date": "2026-01-26",
    "Series": "2026-01-26",
    "id": "9",
    "baseballRefKey": "7",
    "gameDateKey": "DET193410090",
    "AwayTeam": "St. Louis Cardinals (1882-present)",
    "HomeTeam": "Detroit Tigers (1901-present)",
    "AwayRunsScored": "11",
    "AwayHits": "17",
    "AwayErrors": "1",
    "HomeRunsScored": "0",
    "HomeHits": "6",
    "HomeErrors": "3",
    "A1_Name": "Martin",
    "A2_Name": "Rothrock",
    "A3_Name": "Frisch",
    "A4_Name": "Medwick",
    "A5_Name": "Collins",
    "A6_Name": "DeLancey",
    "A7_Name": "Orsatti",
    "A8_Name": "Durocher",
    "A9_Name": "Dean",
    "A10_Name": "none",
    "A1_Pos": "3b",
    "A2_Pos": "rf",
    "A3_Pos": "2b",
    "A4_Pos": "lf",
    "A5_Pos": "1b",
    "A6_Pos": "c",
    "A7_Pos": "cf",
    "A8_Pos": "ss",
    "A9_Pos": "p",
    "A10_Pos": "dh",
    "H1_Name": "White",
    "H2_Name": "Cochrane",
    "H3_Name": "Gehringer",
    "H4_Name": "Goslin",
    "H5_Name": "Rogell",
    "H6_Name": "Greenberg",
    "H7_Name": "Owen",
    "H8_Name": "Fox",
    "H9_Name": "Auker",
    "H10_Name": "none",
    "H1_Pos": "cf",
    "H2_Pos": "c",
    "H3_Pos": "2b",
    "H4_Pos": "lf",
    "H5_Pos": "ss",
    "H6_Pos": "1b",
    "H7_Pos": "3b",
    "H8_Pos": "rf",
    "H9_Pos": "p",
    "H10_Pos": "dh",
    "LinkSabr": "https://sabr.org/gamesproj/game/october-9-1934-a-case-for-judge-landis-medwick-tossed-in-world-series-melee-as-cardinals-win-game-7/"
  }
]