[
  {
    "Date": "24-12-07",
    "Series": "Quincy",
    "id": 0,
    "AwayTeam": "na",
    "HomeTeam": "na",
    "AwayRunsScored": 0,
    "AwayHits": 0,
    "AwayErrors": 0,
    "HomeRunsScored": 0,
    "HomeHits": 0,
    "HomeErrors": 0,
    "Author": "na",
    "LinkSabr": "https://www.baseball-reference.com/boxes/BOS/BOS194607142.shtml",
    "LinkBox": "TEST",
    "A1_Name": "__",
    "A2_Name": "To BEGIN",
    "A3_Name": "",
    "A4_Name": "#starting9",
    "A5_Name": "YELLOW",
    "A6_Name": "button",
    "A7_Name": "_",
    "A8_Name": "_",
    "A9_Name": "_",
    "A10_Name": "_",
    "A1_Pos": "_",
    "A2_Pos": "_",
    "A3_Pos": "_",
    "A4_Pos": "_",
    "A5_Pos": "_",
    "A6_Pos": "_",
    "A7_Pos": "_",
    "A8_Pos": "_",
    "A9_Pos": "_",
    "A10_Pos": "LINEUP",
    "H1_Name": "_",
    "H2_Name": "playing",
    "H3_Name": "_",
    "H4_Name": "press",
    "H5_Name": "START",
    "H6_Name": "Above",
    "H7_Name": "_",
    "H8_Name": "_",
    "H9_Name": "_",
    "H10_Name": "_",
    "H1_Pos": "_",
    "H2_Pos": "_",
    "H3_Pos": "_",
    "H4_Pos": "_",
    "H5_Pos": "_",
    "H6_Pos": "_",
    "H7_Pos": "_",
    "H8_Pos": "_",
    "H9_Pos": "_",
    "H10_Pos": "-"
  },
  {
    "Date": "24-12-07",
    "Series": "Quincy",
    "id": 1,
    "AwayTeam": "Detroit Tigers (1901-present)",
    "HomeTeam": "Chicago White Sox (1901-present)",
    "AwayRunsScored": 4,
    "AwayHits": 5,
    "AwayErrors": 0,
    "HomeRunsScored": 0,
    "HomeHits": 0,
    "HomeErrors": 0,
    "Author": "https://sabr.org/authors/nathan-bierma/",
    "LinkSabr": "https://sabr.org/gamesproj/game/april-7-1984-jack-morris-throws-a-no-hitter-against-the-white-sox/",
    "LinkBox": "http://www.baseball-reference.com/boxes/CHA/CHA198404070.shtml",
    "A1_Name": "Whitaker",
    "A2_Name": "Trammell",
    "A3_Name": "Garbey",
    "A4_Name": "Parrish",
    "A5_Name": "Herndon",
    "A6_Name": "Allen",
    "A7_Name": "Lemon",
    "A8_Name": "Gibson",
    "A9_Name": "Brookens",
    "A10_Name": "Morris",
    "A1_Pos": "2b",
    "A2_Pos": "ss",
    "A3_Pos": "1b",
    "A4_Pos": "c",
    "A5_Pos": "lf",
    "A6_Pos": "dh",
    "A7_Pos": "cf",
    "A8_Pos": "rf",
    "A9_Pos": "3b",
    "A10_Pos": "p",
    "H1_Name": "R. Law",
    "H2_Name": "Fisk",
    "H3_Name": "Baines",
    "H4_Name": "Luzinski",
    "H5_Name": "Kittle",
    "H6_Name": "Paciorek",
    "H7_Name": "V. Law",
    "H8_Name": "Fletcher",
    "H9_Name": "Cruz",
    "H10_Name": "Bannister",
    "H1_Pos": "cf",
    "H2_Pos": "c",
    "H3_Pos": "rf",
    "H4_Pos": "dh",
    "H5_Pos": "lf",
    "H6_Pos": "1b",
    "H7_Pos": "3b",
    "H8_Pos": "ss",
    "H9_Pos": "2b",
    "H10_Pos": "p"
  },
  {
    "Date": "24-12-07",
    "Series": "Quincy",
    "id": 2,
    "AwayTeam": "New York Giants (1883-1957)",
    "HomeTeam": "Brooklyn Dodgers (1884-1957)",
    "AwayRunsScored": 1,
    "AwayHits": 3,
    "AwayErrors": 0,
    "HomeRunsScored": 6,
    "HomeHits": 6,
    "HomeErrors": 1,
    "Author": "https://sabr.org/authors/steven-c-weiner/",
    "LinkSabr": "https://sabr.org/gamesproj/game/september-9-1956-don-drysdales-homer-three-hitter-beat-giants-for-the-fourth-time/",
    "LinkBox": "https://www.baseball-reference.com/boxes/BRO/BRO195609090.shtml",
    "A1_Name": "Mueller",
    "A2_Name": "Schoendienst",
    "A3_Name": "Mays",
    "A4_Name": "Thompson",
    "A5_Name": "Brandt",
    "A6_Name": "White",
    "A7_Name": "Sarni",
    "A8_Name": "Spencer",
    "A9_Name": "Surkont",
    "A10_Name": "none",
    "A1_Pos": "rf",
    "A2_Pos": "2b",
    "A3_Pos": "cf",
    "A4_Pos": "3b",
    "A5_Pos": "lf",
    "A6_Pos": "1b",
    "A7_Pos": "c",
    "A8_Pos": "ss",
    "A9_Pos": "p",
    "A10_Pos": "dh",
    "H1_Name": "Gilliam",
    "H2_Name": "Reese",
    "H3_Name": "Snider",
    "H4_Name": "Robinson",
    "H5_Name": "Amoros",
    "H6_Name": "Furillo",
    "H7_Name": "Hodges",
    "H8_Name": "Walker",
    "H9_Name": "Drysdale",
    "H10_Name": "none",
    "H1_Pos": "2b",
    "H2_Pos": "ss",
    "H3_Pos": "cf",
    "H4_Pos": "3b",
    "H5_Pos": "lf",
    "H6_Pos": "rf",
    "H7_Pos": "1b",
    "H8_Pos": "c",
    "H9_Pos": "p",
    "H10_Pos": "dh"
  },
  {
    "Date": "24-12-07",
    "Series": "Quincy",
    "id": 3,
    "AwayTeam": "California Angels (1961-present)",
    "HomeTeam": "Minnesota Twins (1901-present)",
    "AwayRunsScored": 0,
    "AwayHits": 2,
    "AwayErrors": 0,
    "HomeRunsScored": 6,
    "HomeHits": 6,
    "HomeErrors": 1,
    "Author": "https://sabr.org/authors/sarah-johnson/",
    "LinkSabr": "https://sabr.org/gamesproj/game/september-25-1976-late-season-official-scoring-controversy-ended-by-ninth-inning-hit/",
    "LinkBox": "https://www.baseball-reference.com/boxes/MIN/MIN197609250.shtml",
    "A1_Name": "Collins",
    "A2_Name": "Remy",
    "A3_Name": "Jones",
    "A4_Name": "Solaita",
    "A5_Name": "Guerrero",
    "A6_Name": "Humphrey",
    "A7_Name": "Jackson",
    "A8_Name": "Lopez",
    "A9_Name": "Chalk",
    "A10_Name": "Ryan",
    "A1_Pos": "lf",
    "A2_Pos": "2b",
    "A3_Pos": "cf",
    "A4_Pos": "1b",
    "A5_Pos": "dh",
    "A6_Pos": "c",
    "A7_Pos": "3b",
    "A8_Pos": "rf",
    "A9_Pos": "ss",
    "A10_Pos": "p",
    "H1_Name": "Braun",
    "H2_Name": "Smalley",
    "H3_Name": "Carew",
    "H4_Name": "Bostock",
    "H5_Name": "Hisle",
    "H6_Name": "Wynegar",
    "H7_Name": "Cubbage",
    "H8_Name": "Ford",
    "H9_Name": "Randall",
    "H10_Name": "Goltz",
    "H1_Pos": "dh",
    "H2_Pos": "ss",
    "H3_Pos": "1b",
    "H4_Pos": "cf",
    "H5_Pos": "lf",
    "H6_Pos": "c",
    "H7_Pos": "3b",
    "H8_Pos": "rf",
    "H9_Pos": "2b",
    "H10_Pos": "p"
  },
  {
    "Date": "24-12-07",
    "Series": "Quincy",
    "id": 4,
    "AwayTeam": "Philadelphia Athletics (1901-1954)",
    "HomeTeam": "New York Yankees (1903-present)",
    "AwayRunsScored": 4,
    "AwayHits": 7,
    "AwayErrors": 2,
    "HomeRunsScored": 11,
    "HomeHits": 15,
    "HomeErrors": 0,
    "Author": "https://sabr.org/authors/kurt-blumenau/",
    "LinkSabr": "https://sabr.org/gamesproj/game/june-8-1934-as-rookie-mort-flohrs-wayward-first-pitch-nails-babe-ruth/",
    "LinkBox": "https://www.baseball-reference.com/boxes/NYA/NYA193406080.shtml",
    "A1_Name": "Williams",
    "A2_Name": "Cramer",
    "A3_Name": "Johnson",
    "A4_Name": "Foxx",
    "A5_Name": "McNair",
    "A6_Name": "Miller",
    "A7_Name": "Higgins",
    "A8_Name": "Hayes",
    "A9_Name": "Marcum",
    "A10_Name": "none",
    "A1_Pos": "2b",
    "A2_Pos": "cf",
    "A3_Pos": "lf",
    "A4_Pos": "1b",
    "A5_Pos": "ss",
    "A6_Pos": "rf",
    "A7_Pos": "3b",
    "A8_Pos": "c",
    "A9_Pos": "p",
    "A10_Pos": "dh",
    "H1_Name": "Combs",
    "H2_Name": "Rolfe",
    "H3_Name": "Ruth",
    "H4_Name": "Gehrig",
    "H5_Name": "Hoag",
    "H6_Name": "Lazzeri",
    "H7_Name": "Dickey",
    "H8_Name": "Crosetti",
    "H9_Name": "Gomez",
    "H10_Name": "none",
    "H1_Pos": "cf",
    "H2_Pos": "ss",
    "H3_Pos": "rf",
    "H4_Pos": "1b",
    "H5_Pos": "lf",
    "H6_Pos": "2b",
    "H7_Pos": "c",
    "H8_Pos": "3b",
    "H9_Pos": "p",
    "H10_Pos": "dh"
  },
  {
    "Date": "24-12-07",
    "Series": "Quincy",
    "id": 5,
    "AwayTeam": "Chicago White Sox (1901-present)",
    "HomeTeam": "Minnesota Twins (1901-present)",
    "AwayRunsScored": 12,
    "AwayHits": 16,
    "AwayErrors": 2,
    "HomeRunsScored": 19,
    "HomeHits": 18,
    "HomeErrors": 0,
    "Author": "https://sabr.org/authors/jim-mckernon/",
    "LinkSabr": "https://sabr.org/gamesproj/game/june-26-1977-adams-8-rbis-carews-5-runs-lead-twins-in-slugfest/",
    "LinkBox": "http://www.baseball-reference.com/boxes/MIN/MIN197706260.shtml",
    "A1_Name": "Bannister",
    "A2_Name": "Lemon",
    "A3_Name": "L. Johnson",
    "A4_Name": "Zisk",
    "A5_Name": "Soderholm",
    "A6_Name": "Nordhagen",
    "A7_Name": "Downing",
    "A8_Name": "Orta",
    "A9_Name": "Essian",
    "A10_Name": "Stone",
    "A1_Pos": "ss",
    "A2_Pos": "cf",
    "A3_Pos": "1b",
    "A4_Pos": "dh",
    "A5_Pos": "3b",
    "A6_Pos": "rf",
    "A7_Pos": "lf",
    "A8_Pos": "2b",
    "A9_Pos": "c",
    "A10_Pos": "p",
    "H1_Name": "Bostock",
    "H2_Name": "Smalley",
    "H3_Name": "Carew",
    "H4_Name": "Wynegar",
    "H5_Name": "Hisle",
    "H6_Name": "Adams",
    "H7_Name": "Chiles",
    "H8_Name": "Cubbage",
    "H9_Name": "Wilfong",
    "H10_Name": "Butler",
    "H1_Pos": "cf",
    "H2_Pos": "ss",
    "H3_Pos": "1b",
    "H4_Pos": "c",
    "H5_Pos": "lf",
    "H6_Pos": "rf",
    "H7_Pos": "dh",
    "H8_Pos": "3b",
    "H9_Pos": "2b",
    "H10_Pos": "p"
  },
  {
    "Date": "24-12-07",
    "Series": "Quincy",
    "id": 6,
    "AwayTeam": "Toronto Blue Jays (1977-present)",
    "HomeTeam": "Houston Astros (1962-present)",
    "AwayRunsScored": 2,
    "AwayHits": 6,
    "AwayErrors": 2,
    "HomeRunsScored": 8,
    "HomeHits": 13,
    "HomeErrors": 1,
    "Author": "https://sabr.org/authors/john-burbridge/",
    "LinkSabr": "https://sabr.org/gamesproj/game/august-2-2014-jon-singletons-inside-the-park-home-run-highlights-astros-win-over-blue-jays/",
    "LinkBox": "https://www.baseball-reference.com/boxes/HOU/HOU201408020.shtml",
    "A1_Name": "Reyes",
    "A2_Name": "Cabrera",
    "A3_Name": "Bautista",
    "A4_Name": "Reimold",
    "A5_Name": "Valencia",
    "A6_Name": "Tolleson",
    "A7_Name": "Thole",
    "A8_Name": "Goins",
    "A9_Name": "Gose",
    "A10_Name": "Dickey",
    "A1_Pos": "ss",
    "A2_Pos": "lf",
    "A3_Pos": "rf",
    "A4_Pos": "dh",
    "A5_Pos": "1b",
    "A6_Pos": "3b",
    "A7_Pos": "c",
    "A8_Pos": "2b",
    "A9_Pos": "cf",
    "A10_Pos": "p",
    "H1_Name": "Altuve",
    "H2_Name": "Grossman",
    "H3_Name": "Carter",
    "H4_Name": "Castro",
    "H5_Name": "Krauss",
    "H6_Name": "Singleton",
    "H7_Name": "Dominguez",
    "H8_Name": "Marisnick",
    "H9_Name": "Petit",
    "H10_Name": "Oberholtzer",
    "H1_Pos": "2b",
    "H2_Pos": "rf",
    "H3_Pos": "dh",
    "H4_Pos": "c",
    "H5_Pos": "lf",
    "H6_Pos": "1b",
    "H7_Pos": "3b",
    "H8_Pos": "cf",
    "H9_Pos": "ss",
    "H10_Pos": "p"
  },
  {
    "Date": "24-12-07",
    "Series": "Quincy",
    "id": 7,
    "AwayTeam": "Kansas City Packers (1914-1915)",
    "HomeTeam": "Indianapolis Hoosiers (1914)",
    "AwayRunsScored": 2,
    "AwayHits": 11,
    "AwayErrors": 1,
    "HomeRunsScored": 5,
    "HomeHits": 12,
    "HomeErrors": 0,
    "Author": "https://sabr.org/authors/thomas-e-merrick/",
    "LinkSabr": "https://sabr.org/gamesproj/game/june-24-1914-kaiserling-kauff-lead-hoosiers-past-packers-extending-winning-streak-to-15/",
    "LinkBox": "https://www.baseball-reference.com/boxes/IND/IND191406240.shtml",
    "A1_Name": "Chadbourne",
    "A2_Name": "Gilmore",
    "A3_Name": "Kenworthy",
    "A4_Name": "Easterly",
    "A5_Name": "Perring",
    "A6_Name": "Kruger",
    "A7_Name": "Goodwin",
    "A8_Name": "Stovall",
    "A9_Name": "Cullop",
    "A10_Name": "none",
    "A1_Pos": "lf",
    "A2_Pos": "rf",
    "A3_Pos": "2b",
    "A4_Pos": "c",
    "A5_Pos": "3b",
    "A6_Pos": "cf",
    "A7_Pos": "ss",
    "A8_Pos": "1b",
    "A9_Pos": "p",
    "A10_Pos": "dh",
    "H1_Name": "Campbell",
    "H2_Name": "McKechnie",
    "H3_Name": "Kauff",
    "H4_Name": "LaPorte",
    "H5_Name": "Carr",
    "H6_Name": "Esmond",
    "H7_Name": "Scheer",
    "H8_Name": "Rariden",
    "H9_Name": "Kaiserling",
    "H10_Name": "none",
    "H1_Pos": "cf",
    "H2_Pos": "3b",
    "H3_Pos": "rf",
    "H4_Pos": "2b",
    "H5_Pos": "1b",
    "H6_Pos": "ss",
    "H7_Pos": "lf",
    "H8_Pos": "c",
    "H9_Pos": "p",
    "H10_Pos": "dh"
  },
  {
    "Date": "24-12-07",
    "Series": "Quincy",
    "id": 8,
    "AwayTeam": "Detroit Tigers (1901-present)",
    "HomeTeam": "Cleveland Indians (1915-2021)",
    "AwayRunsScored": 2,
    "AwayHits": 4,
    "AwayErrors": 0,
    "HomeRunsScored": 4,
    "HomeHits": 7,
    "HomeErrors": 1,
    "Author": "https://sabr.org/authors/c-paul-rogers-iii/",
    "LinkSabr": "https://sabr.org/gamesproj/game/august-24-1945-bob-feller-returns-to-baseball-after-world-war-ii/",
    "LinkBox": "https://www.baseball-reference.com/boxes/CLE/CLE194508240.shtml",
    "A1_Name": "Outlaw",
    "A2_Name": "Borom",
    "A3_Name": "Cramer",
    "A4_Name": "Greenberg",
    "A5_Name": "Cullenbine",
    "A6_Name": "York",
    "A7_Name": "Webb",
    "A8_Name": "Richards",
    "A9_Name": "Newhouser",
    "A10_Name": "none",
    "A1_Pos": "3b",
    "A2_Pos": "2b",
    "A3_Pos": "cf",
    "A4_Pos": "lf",
    "A5_Pos": "rf",
    "A6_Pos": "1b",
    "A7_Pos": "ss",
    "A8_Pos": "c",
    "A9_Pos": "p",
    "A10_Pos": "dh",
    "H1_Name": "Cihocki",
    "H2_Name": "Rocco",
    "H3_Name": "Seerey",
    "H4_Name": "Heath",
    "H5_Name": "Meyer",
    "H6_Name": "Ross",
    "H7_Name": "Mackiewicz",
    "H8_Name": "Hayes",
    "H9_Name": "Feller",
    "H10_Name": "none",
    "H1_Pos": "ss",
    "H2_Pos": "1b",
    "H3_Pos": "rf",
    "H4_Pos": "lf",
    "H5_Pos": "2b",
    "H6_Pos": "3b",
    "H7_Pos": "cf",
    "H8_Pos": "c",
    "H9_Pos": "p",
    "H10_Pos": "dh"
  },
  {
    "Date": "24-12-07",
    "Series": "Quincy",
    "id": 9,
    "AwayTeam": "New York Yankees (1903-present)",
    "HomeTeam": "Milwaukee Braves (1953-1965)",
    "AwayRunsScored": 3,
    "AwayHits": 8,
    "AwayErrors": 1,
    "HomeRunsScored": 4,
    "HomeHits": 10,
    "HomeErrors": 0,
    "Author": "https://sabr.org/authors/steve-west/",
    "LinkSabr": "https://sabr.org/gamesproj/game/october-1-1958-spahns-10-inning-complete-game-beats-yankees/",
    "LinkBox": "https://www.baseball-reference.com/boxes/MLN/MLN195810010.shtml",
    "A1_Name": "Bauer",
    "A2_Name": "McDougald",
    "A3_Name": "Mantle",
    "A4_Name": "Howard",
    "A5_Name": "Berra",
    "A6_Name": "Skowron",
    "A7_Name": "Carey",
    "A8_Name": "Kubek",
    "A9_Name": "Ford",
    "A10_Name": "none",
    "A1_Pos": "rf",
    "A2_Pos": "2b",
    "A3_Pos": "cf",
    "A4_Pos": "lf",
    "A5_Pos": "c",
    "A6_Pos": "1b",
    "A7_Pos": "3b",
    "A8_Pos": "ss",
    "A9_Pos": "p",
    "A10_Pos": "dh",
    "H1_Name": "Schoendienst",
    "H2_Name": "Logan",
    "H3_Name": "Mathews",
    "H4_Name": "Aaron",
    "H5_Name": "Adcock",
    "H6_Name": "Covington",
    "H7_Name": "Crandall",
    "H8_Name": "Pafko",
    "H9_Name": "Spahn",
    "H10_Name": "none",
    "H1_Pos": "2b",
    "H2_Pos": "ss",
    "H3_Pos": "3b",
    "H4_Pos": "rf",
    "H5_Pos": "1b",
    "H6_Pos": "lf",
    "H7_Pos": "c",
    "H8_Pos": "cf",
    "H9_Pos": "p",
    "H10_Pos": "dh"
  }
]
